doubleagent/__init__.py
doubleagent/alldel.py
doubleagent/alpacomposite.py
doubleagent/cases.py
doubleagent/deloverlap.py
doubleagent/errorboy.py
doubleagent/horizonpaste.py
doubleagent/listsplit.py
doubleagent/ll2l.py
doubleagent/mix.py
doubleagent/multiplesplit.py
doubleagent/overlapchecker.py
doubleagent/picklemaker.py
doubleagent/picklereader.py
doubleagent/pinset.py
doubleagent/readfile.py
doubleagent/rectangularcroplocation.py
doubleagent/removeAlpha.py
doubleagent/report.py
doubleagent/rightreplace.py
doubleagent/roundimage.py
doubleagent/s2l.py
doubleagent/seleupdate.py
doubleagent/speedcases.py
doubleagent/sublist.py
doubleagent/txt2crop.py
doubleagent/unanimous.py
doubleagent/verticalpaste.py
doubleagent/whiterbg.py
hotshot/__init__.py
hotshot/alldel.py
hotshot/alpacomposite.py
hotshot/cases.py
hotshot/deloverlap.py
hotshot/errorboy.py
hotshot/horizonpaste.py
hotshot/listsplit.py
hotshot/ll2l.py
hotshot/mix.py
hotshot/multiplesplit.py
hotshot/overlapchecker.py
hotshot/picklemaker.py
hotshot/picklereader.py
hotshot/pinset.py
hotshot/readfile.py
hotshot/rectangularcroplocation.py
hotshot/removeAlpha.py
hotshot/report.py
hotshot/rightreplace.py
hotshot/roundimage.py
hotshot/s2l.py
hotshot/seleupdate.py
hotshot/speedcases.py
hotshot/sublist.py
hotshot/txt2crop.py
hotshot/unanimous.py
hotshot/verticalpaste.py
hotshot/whiterbg.py
pyzard/__init__.py
pyzard/alldel.py
pyzard/alpacomposite.py
pyzard/cases.py
pyzard/deloverlap.py
pyzard/errorboy.py
pyzard/horizonpaste.py
pyzard/listfilter.py
pyzard/listsplit.py
pyzard/ll2l.py
pyzard/lst_comprehension.py
pyzard/mix.py
pyzard/multiplesplit.py
pyzard/overlapchecker.py
pyzard/picklemaker.py
pyzard/picklereader.py
pyzard/pinset.py
pyzard/readfile.py
pyzard/rectangularcroplocation.py
pyzard/removeAlpha.py
pyzard/report.py
pyzard/rightreplace.py
pyzard/roundimage.py
pyzard/s2l.py
pyzard/seleupdate.py
pyzard/speedcases.py
pyzard/sublist.py
pyzard/txt2crop.py
pyzard/unanimous.py
pyzard/verticalpaste.py
pyzard/whiterbg.py
pyzard-1.3.dist-info/METADATA
pyzard-1.3.dist-info/WHEEL
pyzard-1.3.dist-info/top_level.txt
pyzard-1.3.dist-info/RECORD
