Metadata-Version: 2.1
Name: pyzard
Version: 1.3
Summary: for our
Home-page: 
Author: didutc
Author-email: natureroot112@gmail.com
License: MIT
Classifier: Programming Language :: Python :: 3
Classifier: License :: OSI Approved :: MIT License
Classifier: Operating System :: OS Independent
